brythoncli
