Metadata-Version: 2.1
Name: brythoncli
Version: 0.2.1
Summary: Another command line interface for the Brython.
Home-page: http://github.com/pylover/brythoncli
License: MIT
Platform: UNKNOWN
Classifier: Development Status :: 4 - Beta
Classifier: Environment :: Console
Classifier: Intended Audience :: Developers
Classifier: License :: OSI Approved :: MIT License
Classifier: Natural Language :: English
Classifier: Operating System :: POSIX :: Linux
Classifier: Programming Language :: Python :: 3.6
Classifier: Programming Language :: Python :: 3.7
Classifier: Programming Language :: Python :: 3.8
Classifier: Topic :: Software Development :: Interpreters
Classifier: Topic :: Text Processing
